time_pretty_breaks/__init__.py
time_pretty_breaks-0.1.1.dist-info/LICENSE
time_pretty_breaks-0.1.1.dist-info/METADATA
time_pretty_breaks-0.1.1.dist-info/WHEEL
time_pretty_breaks-0.1.1.dist-info/top_level.txt
time_pretty_breaks-0.1.1.dist-info/RECORD
