Metadata-Version: 2.1
Name: time-pretty-breaks
Version: 0.1.1
Summary: Split time, date and datetime intervals into "pretty" intervals
Home-page: https://github.com/eos-vision/time_pretty_breaks
Author: Serhii Hulko
Author-email: felytic@gmail.com
License: MIT
Platform: UNKNOWN
Classifier: Development Status :: 4 - Beta
Classifier: Intended Audience :: Developers
Classifier: Operating System :: OS Independent
Classifier: Programming Language :: Python
Classifier: Programming Language :: Python :: 2
Classifier: Programming Language :: Python :: 3
Requires-Dist: python-dateutil
